MANIFEST.in
README.md
requirements.txt
setup.py
sms_platform/__init__.py
sms_platform/ma60.py
sms_platform/yzm360.py
sms_platform.egg-info/PKG-INFO
sms_platform.egg-info/SOURCES.txt
sms_platform.egg-info/dependency_links.txt
sms_platform.egg-info/requires.txt
sms_platform.egg-info/top_level.txt